termchat-0.0.4.dist-info/DESCRIPTION.rst
termchat-0.0.4.dist-info/METADATA
termchat-0.0.4.dist-info/RECORD
termchat-0.0.4.dist-info/WHEEL
termchat-0.0.4.dist-info/entry_points.txt
termchat-0.0.4.dist-info/metadata.json
termchat-0.0.4.dist-info/top_level.txt
termchatDriver/__init__.py
termchatDriver/driver.py
termchatUtils/HChat.py
termchatUtils/__init__.py
termchatUtils/interface.py
